[{"e_id":"14088","title":"美国正式承认苏联","content":"\n    在88年前的今天，1933年11月17日(农历1933年9月30日)，美国正式承认苏联。美国第一任驻苏联大使威廉·C布利特1933年11月17日，美国总统罗斯福宣布美国正式承认苏联政府。罗斯福与苏联外交部长马克西姆-利特维诺夫的广泛接触终于打开了双边关系大门。罗斯福向200名记者宣读了他写给利特维诺夫的信；“我相信我们两国人民会永远保持正常、友好的关系，我们两个国家将为相互的利益和维护世界和平而合作。”苏联方面对于条约的签订作了一些本质问题上的让步、如：许诺不在美国进行共产主义宣传，给予居住在苏联的美国人以宗教自由和一切合法权利；放弃对1918年美国派兵到西伯利亚所造成的损失的所有赔偿要求等。据说这是苏联所签订的条约中最具妥协性的一个。与美国建交是苏联外交战略的重要步骤之一。尽管1933年时美国和苏联在国际事务中所起的作用还不如日后那么显著，但随着国力的进一布强盛，美苏终于成为支配世界的两支最重要的力量。","picNo":"1","picUrl":[{"pic_title":"美国第一任驻苏联大使威廉·C布利特","suffix":"jpeg","id":1,"url":"https://aimgs.oss-cn-shenzhen.aliyuncs.com/history_2021/14088_1.jpeg"}]}]