[{"e_id":"5244","title":"抗战英雄谢晋元遇难","content":"\n    在80年前的今天，1941年4月24日(农历1941年3月28日)，抗战英雄谢晋元遇难。1941年4月24日，在淞沪会战中率领著名的八百壮士死守四行仓库，痛击日军的抗战英雄谢晋元遇难。4月24日，谢晋元在上海租界的“孤军营”内被刺身亡。谢晋元，广东镇平人，1926年黄埔学校第四期毕业，历任排长、连长、营长、参谋主任等职。抗日战争爆发后，任同民军第八十八师二六四旅五二四团副团长，率“八百壮士”孤军坚守上海四行仓库。后奉命退入公共租界，被羁押在胶州路的“孤军营”内。在“孤军营”中，谢晋元仍严格按部队要求治军，官兵每天4点起床，整理内务，然后早操、上课、训练，下午则为操练和自由活动时间。谢晋元还在“孤军营”内办了袜厂、肥皂厂、藤器厂等3个小厂，以自食其力。日军要求租界当局引渡谢晋元未果，便密谋进行劫持。汪精卫也想拉谢晋元下水。面对威胁利诱，谢晋元做好了随时殉国的准备。他写下遗嘱，寄给父母，表示：“如敌劫持之日，即男成仁之时。人生必有一死，此时此境而死，实人生之快事也！”24日晨，部队开始早操，谢晋元巡视营房后，又到伙房检查。他发现上等兵郝鼎诚、张文清、张文顺、尤耀亮藏在伙房不出操，便上前询问原因。郝鼎诚等已受汪氏收买，操铁镐、匕首一拥而上，将谢晋元刺成重伤。凶手当即被擒。谢晋元因流血过多，经抢救无效，于下午6点死去。重庆各界隆重悼谢晋元团长遇难","picNo":"2","picUrl":[{"pic_title":"1941年4月24日，在淞沪会战中率领著名的八百壮士死守四行仓库，痛击日军的抗战英雄谢晋元遇难。","suffix":"jpeg","id":1,"url":"https://aimgs.oss-cn-shenzhen.aliyuncs.com/history_2021/5244_1.jpeg"},{"pic_title":"重庆各界隆重悼谢晋元团长遇难","suffix":"jpeg","id":2,"url":"https://aimgs.oss-cn-shenzhen.aliyuncs.com/history_2021/5244_2.jpeg"}]}]