[{"e_id":"15189","title":"中国军事法庭设立","content":"\n    在75年前的今天，1946年12月15日(农历1946年11月22日)，中国军事法庭设立。\n\t1946年12月15日，中国军事法庭设立。\n\n\t中国军事法庭于1946年12月15日设立，除收审在中国捕获的有关日本战犯外，还将南京大屠杀重要罪犯谷寿夫、向井敏明、野田毅、田中军吉等先后引渡来华受审。1946年12月21日，中国军事法庭审讯谷寿夫时，400余人出庭作证。12月31日，该庭检察官对谷犯起诉。集体屠杀列为28案，零散屠杀列为858案。1947年2月6日至8日，中国军事法庭在励志社对战犯谷寿夫进行了为期3天的公审，有80余名证人出庭陈述谷寿夫等部日军在南京的暴行，其中有外籍证人3名。3月10日，中国军事法庭在进一步调查、核实的基础上，确认：“我被俘虏军民遭日军用机枪集体射杀并焚尸灭迹者，有单耀亭等19万余人”，被日军零星屠杀“其尸体经慈善机构收埋者15万余具。被害总数达30万以上”。“谷寿夫在作战期间，共同纵兵屠杀俘虏及非战斗人员，并强奸、抢劫、破坏财产”，被判处死刑。4月26日，在南京执行枪决。此后，中国军事法庭又对从无锡至南京沿途进行“杀人比赛”的暴徒向井敏明、野田毅和屠杀南京同胞300余名的刽子手田中军吉等3名战犯，进行审判。1947年12月18日判处死刑，并于1948年1月28日在南京执行枪决。\n\n\t\n\n\t中国军事法庭\n\n\t\n\n\t位于南京市中山东路307号，现为钟山宾馆黄埔厅礼堂。","picNo":"2","picUrl":[{"pic_title":"中国军事法庭","suffix":"jpeg","id":1,"url":"https://aimgs.oss-cn-shenzhen.aliyuncs.com/history_2021/15189_1.jpeg"},{"pic_title":"位于南京市中山东路307号，现为钟山宾馆黄埔厅礼堂。","suffix":"jpeg","id":2,"url":"https://aimgs.oss-cn-shenzhen.aliyuncs.com/history_2021/15189_2.jpeg"}]}]