[{"e_id":"10675","title":"所罗门群岛以东海战爆发","content":"\n    在79年前的今天，1942年8月24日(农历1942年7月13日)，瓜岛争夺战。\n\t\n\n\t日本龙骧号航空母舰\n\n\t1942年8月24日，所罗门群岛以东海战爆发。日军出动大规模舰队，掩护增援部队向瓜达尔卡纳尔进发，并企图引诱美国航母特混舰队进行决战。中午时分，担任诱饵任务的以轻型航母“龙骧”号为首的日本牵制舰队被美军发现，遭到美军“萨拉托加”号航母的38架舰载机集中攻击，“龙骧”号被连续击中10颗炸弹和1条鱼雷，于次日沉没。日军主力舰队的两艘大型航母(翔鹤、瑞鹤号)趁机对美军航母发动攻击，将“企业”号航母炸伤。与此同时，日舰队的先遣群和增援群先后遭到美机攻击，1艘运兵船和1艘驱逐舰被击沉，“千岁”号水上飞机母舰以及巡洋舰、驱逐舰各一艘被炸伤，增援船队搭载的陆军部队损失过半，被迫中途返回出发地，从而使增援瓜岛的行动成为泡影。\n\n\t  \n\n\t点评：龙骧号这艘从中国空军轰炸中侥幸逃脱的贼船终于完蛋了","picNo":"2","picUrl":[{"pic_title":"日本龙骧号航空母舰","suffix":"jpeg","id":1,"url":"https://aimgs.oss-cn-shenzhen.aliyuncs.com/history_2021/10675_1.jpeg"},{"pic_title":"点评：龙骧号这艘从中国空军轰炸中侥幸逃脱的贼船终于完蛋了","suffix":"jpeg","id":2,"url":"https://aimgs.oss-cn-shenzhen.aliyuncs.com/history_2021/10675_2.jpeg"}]}]