[{"e_id":"3642","title":"瑞典女作家拉格洛芙病逝","content":"\n    在81年前的今天，1940年3月16日(农历1940年2月8日)，瑞典女作家拉格洛芙病逝。\n塞尔玛·拉格洛芙(SelmaLagerlof，1858-1940)瑞典女作家。生于瑞典西部韦姆兰省玛巴卡村的贵族军官家庭。3岁时因下肢疾患，行走艰难，主要靠书籍和会讲故事的外祖母朝夕相伴，接触了大量的童话、神州的民间传说等。\n1882年，拉格洛芙入首都斯德哥尔摩皇室女子师范学院学习，受到科学的洗礼。她博览群书，广泛涉猎了哲学、神学和文学等各个领域的知识，毕业后小学地理老师达10年之久，并于业余从事写作。1891年，第一部长篇小说问世，受到丹麦著名文学批评家勃兰兑斯的赏识，一举成名。此后又发表了优秀短篇小说集《无形的锁链》(1894)、《昆加哈拉的王后们》(1899)、长篇小说《伪基督的奇迹》(1897)和《耶路撒冷》(1901-1902)等。《耶路撒冷》被称为达到艺术最高境界的“国家的史诗”。\n\n1897年，拉格洛芙在瑞典中部的法隆市定居。1906年应瑞典一位小学校长的请求，答应写一本适合儿童读的书。年近50岁的作家，为了搜集有关资料，忍受着腿疾带来的巨大痛苦，跋山涉水，在全国进行实地考查。她在认真研究飞禽走兽的生活习性和规律、调查各地的风俗习惯和民间传说的基础上，终于完成了举世闻名的童话小说《尼尔斯的奇遇》(直译为《尼尔斯·豪尔耶松传奇般地周游瑞典》)。这部作品使作家从此与安徒生齐名。\n在她精彩动人的得奖演说中，她以赤子之心，对兹父、乡土和赐与她灵感的作家、思想家们表达了由衷的敬爱和赞美之情。这之后，她又创作了《利纽克罗纳的家》(1911)、《死神的车夫》(1912)、《葡萄牙的皇帝》(1914)、《妖精和人》(1915-1921)、《罪犯们》(1918)、《勒温萧德》三部曲(1925-1928)、《安娜·史威特》等。晚年回到祖居玛巴卡田庄定居，仍笔耕不辍，又写了《一个孩子的回忆》(1930)、《日记》(1932)、《圣诞节的故事》(1938)等重要作品。\n1940年3月16日病逝，享年82岁。\n\n1909年，“由于她作品中特有的高贵的理想主义、丰饶的想象力、平易而优美的风格”，而获得了诺贝尔文学奖。\n评论：毅力坚强、多产的诺贝尔文学奖得主","picNo":"3","picUrl":[{"pic_title":"","suffix":"jpeg","id":1,"url":"https://aimgs.oss-cn-shenzhen.aliyuncs.com/history_2021/3642_1.jpeg"},{"pic_title":"","suffix":"jpeg","id":2,"url":"https://aimgs.oss-cn-shenzhen.aliyuncs.com/history_2021/3642_2.jpeg"},{"pic_title":"","suffix":"jpeg","id":3,"url":"https://aimgs.oss-cn-shenzhen.aliyuncs.com/history_2021/3642_3.jpeg"}]}]