[{"day":"12/6","date":"465年12月6日","title":"南朝刘宋将领沈庆之逝世","e_id":"14835"},{"day":"12/6","date":"1877年12月6日","title":"发明大王爱迪生发明世界第一台留声机","e_id":"14836"},{"day":"12/6","date":"1892年12月6日","title":"世界著名电子电器之父西门子逝世","e_id":"14837"},{"day":"12/6","date":"1905年12月6日","title":"探险家阿蒙森探明地球磁极","e_id":"14838"},{"day":"12/6","date":"1907年12月6日","title":"清末立宪运动兴起","e_id":"14839"},{"day":"12/6","date":"1917年12月6日","title":"芬兰宣布脱离俄国独立","e_id":"14840"},{"day":"12/6","date":"1922年12月6日","title":"爱尔兰自由邦成立","e_id":"14841"},{"day":"12/6","date":"1938年12月6日","title":"周恩来同蒋介石商谈两党合作","e_id":"14842"},{"day":"12/6","date":"1941年12月6日","title":"英国对芬兰、罗马尼亚和匈牙利三国宣战","e_id":"14843"},{"day":"12/6","date":"1943年12月6日","title":"三位大人物商定征服德国的计划","e_id":"14844"},{"day":"12/6","date":"1945年12月6日","title":"微波炉问世","e_id":"14845"},{"day":"12/6","date":"1957年12月6日","title":"美国实验性人造卫星爆炸","e_id":"14846"},{"day":"12/6","date":"1957年12月6日","title":"首都一千多名科学干部下乡劳动锻炼","e_id":"14847"},{"day":"12/6","date":"1966年12月6日","title":"第一届亚洲新运会结束","e_id":"14848"},{"day":"12/6","date":"1979年12月6日","title":"西单“民主墙”禁贴大字报","e_id":"14849"},{"day":"12/6","date":"1979年12月6日","title":"邓小平谈“小康”","e_id":"14850"},{"day":"12/6","date":"1979年12月6日","title":"台湾美丽岛事件发生","e_id":"14851"},{"day":"12/6","date":"1984年12月6日","title":"中国新闻学会成立","e_id":"14852"},{"day":"12/6","date":"1984年12月6日","title":"英文版《邓小平文集》在伦敦出版","e_id":"14853"},{"day":"12/6","date":"1985年12月6日","title":"三北防护林体系一期工程结束","e_id":"14854"},{"day":"12/6","date":"1985年12月6日","title":"我军卓越的政治工作者谭冠三逝世","e_id":"14855"},{"day":"12/6","date":"1986年12月6日","title":"泥沙学家钱宁逝世","e_id":"14856"},{"day":"12/6","date":"1989年12月6日","title":"我国首批转基因兔问世","e_id":"14857"},{"day":"12/6","date":"1992年12月6日","title":"印度爆发教族骚乱","e_id":"14858"},{"day":"12/6","date":"1994年12月6日","title":"朝美互设联络处","e_id":"14859"},{"day":"12/6","date":"1995年12月6日","title":"中俄朝韩蒙签署图们江地区开发协定","e_id":"14860"},{"day":"12/6","date":"1996年12月6日","title":"庐山被批准为“世界文化景观”","e_id":"14861"},{"day":"12/6","date":"1997年12月6日","title":"我国早期女企业家董竹君逝世","e_id":"14862"},{"day":"12/6","date":"1997年12月6日","title":"俄空军运输机坠落民宅","e_id":"14863"},{"day":"12/6","date":"1997年12月6日","title":"首次南极跳伞三名探险者丧生","e_id":"14864"},{"day":"12/6","date":"1998年12月6日","title":"查韦斯当选委内瑞拉总统","e_id":"14865"},{"day":"12/6","date":"1998年12月6日","title":"第十三届曼谷亚运会开幕","e_id":"14866"},{"day":"12/6","date":"1999年12月6日","title":"南疆铁路全线开通运营","e_id":"14867"},{"day":"12/6","date":"2001年12月6日","title":"中国航油在新加坡成功上市","e_id":"14868"},{"day":"12/6","date":"2001年12月6日","title":"广西壮族自治区常务副主席刘知炳被查处","e_id":"14869"},{"day":"12/6","date":"2002年12月6日","title":"我科学家发现核反应堆中微子消失现象","e_id":"14870"},{"day":"12/6","date":"2007年12月6日","title":"印度成功进行导弹拦截试验","e_id":"14871"},{"day":"12/6","date":"2012年12月6日","title":"国家发改委副主任、国家能源局局长刘铁男被查","e_id":"14872"},{"day":"12/6","date":"2012年12月6日","title":"四川省委原副书记李春城被查","e_id":"14873"},{"day":"12/6","date":"2013年12月6日","title":"江西省人大常委会原副主任陈安众被查","e_id":"14874"},{"day":"12/6","date":"2015年12月6日","title":"开国少将刘居英逝世","e_id":"14875"},{"day":"12/6","date":"2019年12月6日","title":"世界首例“猪猴嵌合体”中国诞生","e_id":"14876"}]