[{"e_id":"11746","title":"墨西哥发生强烈地震","content":"\n    在36年前的今天，1985年9月19日(农历1985年8月5日)，墨西哥发生强烈地震。\n\n\n墨西哥地震\n1985年9月19日清晨7点19分，墨西哥发生里氏7.8级强烈地震，首都墨西哥城35%的建筑物遭到不同程度的破坏。市中心的许多房屋，顷刻之间变成一片废墟，不久前刚刚庆祝落成71周年的著名的雷布斯大旅馆全部毁坏。著名的华雷斯大街有好几段变成残垣断壁。市内一些地方由于煤气管破裂，引起大火。\n地震发生后，墨西哥城大部分地区交通中断，地铁全部停驶，国际机场暂时关闭。市区水电煤气被切断，市内电话和长途电话也中断了。\n墨西哥联邦政府和墨西哥城联邦区政府立即组织抢险救灾，德拉马德里总统迅速赶到灾区现场视察，并组织召开内阁会议，部署救灾措施。\n这次地震震中在墨西哥城西南大约400公里处的太平洋海岸，波及墨西哥城和墨西哥沿海的3个州。9月19日清晨发生里氏7.8级地震之后，20日晚上在同一地区又发生了一次里氏6.5级的地震。到9月25日，墨西哥共发生了60次里氏3.5到5.5级的余震。截至9月24日，共有一千多幢楼房严重受损，其中七百多幢完全倒塌，死亡3500人，受伤的(包括轻伤在内)有4万人，还有32000灾民无家可归。\n墨西哥大地震后，许多国家和国际组织以及个人想尽一切办法向墨西哥人民伸出了援助之手。几十架不同国籍的飞机给灾民带来了亟需的药品、食物、衣物和抢险设备等。墨西哥城国际机场变成了连接墨西哥和各国人民友谊的空中走廊。联合国大会9月24日一致通过决议，呼吁所有国家向墨西哥提供慷慨的援助，帮助墨西哥做好救灾和重建灾区的工作。\n大地震后的第5天，墨西哥城开始恢复正常生活。第20天，在墨西哥城成立了全国重建委员会。德拉马德里总统阐述了这个委员会的组成、职能和重建工作需要达到的目标。在他提出的9项重建任务中，不仅包括安置难民，优先修复受到破坏的住宅、医院、学校以及通讯、供水系统等公共设施，还包括疏散过于集中的机构，鼓励一部分中央机关和企业到地方去。这是墨西哥城重建工作的一个重要特点，受到灾民们的赞同。\n墨西哥城的瓜胡特莫克区是大地震的重灾区，这一带多是人口稠密的老式住宅，街道狭窄，重建工作十分艰巨。墨西哥政府投入大量人力、物力，首先重建这个区的学校、医院和居民住宅。在地震一周年之际，全区大部分学校都已修复，一部分灾民已住进新居。墨西哥政府计划在地震后两年之内基本解决所有灾民的住房困难。经历了地震灾难的墨西哥人民对未来的生活充满信心。\n\n\n\n1985年：墨西哥(墨西哥城)/ 震级(里氏)：8.1 / 死亡人数：10，000 / 财产损失：40亿美元","picNo":"2","picUrl":[{"pic_title":"墨西哥地震","suffix":"jpeg","id":1,"url":"https://aimgs.oss-cn-shenzhen.aliyuncs.com/history_2021/11746_1.jpeg"},{"pic_title":"","suffix":"jpeg","id":2,"url":"https://aimgs.oss-cn-shenzhen.aliyuncs.com/history_2021/11746_2.jpeg"}]}]