[{"e_id":"11758","title":"联合国贸发会议发表贸易和发展报告","content":"\n    在25年前的今天，1996年9月19日(农历1996年8月7日)，联合国贸发会议发表贸易和发展报告。1996年9月19日，联合国贸易和发展会议发表1996年贸易和发展报告认为，世界经济自1993年走出衰退后，至今虽年年保持增长，但增长速度呈放慢趋势。报告说，1993年开始的世界经济复苏比以往几次复苏都乏力。1994年全球产值增长了2.8，去年仅增长2.4，大大低于预计的超过3。1996年的增长率预计仍为2.4。1995年，发达国家的经济增长率从前年的2.8下降到了2，1996年预计只有1.9。报告认为，发达国家增长乏力的主要原因是政府过分注重控制通货膨胀和削减预算。在发达国家中，美国经济形势好于其他国家，在过去两年中共创造了300多万个就业机会，1996年的增长率估计可达2.2。相比之下，日本和西欧的失业率却一直在上升，且近期内难有改善。日本经济去年底终于摆脱了4年的停滞，增长率在1996年可能达2.1。但报告认为，从长远看，日本应加强经济结构调整，扩大国内需求。报告说，1995年发展中国家的平均经济增长率从1994年的4.7降到4，但1996年可望达到4.5。中国仍是世界上经济增长最快的国家之一，1995年的增长率达到10.2，虽然政府采取措施防止经济过热会使增长速度放慢，但1996年的增长率仍可能达到9。除中国外，其他亚洲发展中国家去年经济平均增长6.3，明显高于其他地区，1996年的增长率估计为6.1。但由于国际竞争的加剧，不少东南亚国家目前出现了出口增长放慢和国际收支逆差扩大的新问题。非洲国家得益于原材料价格的上升，1995年经济增长了2.8，达到10年来的最高水平，1996年的增长率预计将为3.1。报告认为，墨西哥货币危机对拉美国家经济的影响比原先估计的要严重。该地区1995年的经济增长率从前年的4.9跌到0.7，1996年的增长率可望恢复到2.4。中东欧国家1995年总体经济形势得到改善，中欧国家经济增长率达5.3。独联体很多国家的经济仍是负增长，但下降速度大幅度减缓。1996年中东欧国家的平均经济增长率预计为0.3。","picNo":"0","picUrl":[]}]