[{"e_id":"4126","title":"美国抓获菲律宾的反抗运动领袖","content":"\n    在120年前的今天，1901年3月27日(农历1901年2月8日)，美国抓获菲律宾的反抗运动领袖。阿奎纳多被捕后登上美国炮艇1901年3月27日，无畏的菲律宾领导人埃米利欧-阿奎纳多被美国人抓获。他是在伊洛伊洛省的反抗头目投降后不到两个月被捕的。这鼓舞了华盛顿，使华盛顿有希望最终结束在菲律宾的这场长时间的反抗运动。逮捕这位反抗领导人的计划是由弗雷德里克-芬斯顿将军策划的。他化装成一名反抗者的囚犯，使阿奎纳多上当，暴露了他的司令部所在地。早在1898年美国接管菲律宾之前，阿奎纳多就已经是一位著名的民族主义领导人。1896年他领导了一次抗击西班牙长达400年之久统治的暴动。","picNo":"1","picUrl":[{"pic_title":"阿奎纳多被捕后登上美国炮艇","suffix":"jpeg","id":1,"url":"https://aimgs.oss-cn-shenzhen.aliyuncs.com/history_2021/4126_1.jpeg"}]}]