[{"e_id":"4135","title":"多特蒙德第25届世界乒乓球锦标赛开幕","content":"\n    在62年前的今天，1959年3月27日(农历1959年2月19日)，多特蒙德第25届世界乒乓球锦标赛开幕。这是1959年4月22日，容国团手捧冠军奖杯载誉归来。1959年3月27日至4月6日在原西德的多特蒙德举行了。1959年4月5日，容国团在德国多特蒙德举行的第25届世界乒乓球锦标赛上，打败曾7次获得世界乒乓球男子单打冠军的匈牙利运动员西多，获男子单打冠军。这是中国在世界性体育比赛中获得的第一个世界冠军。这次比赛集中了38个国家的240名优秀选手,中国年仅21岁的选手容国团夺得了男子单打的世界冠军,也是我国选手首次获得男子单打冠军。","picNo":"1","picUrl":[{"pic_title":"这是1959年4月22日，容国团手捧冠军奖杯载誉归来。","suffix":"jpeg","id":1,"url":"https://aimgs.oss-cn-shenzhen.aliyuncs.com/history_2021/4135_1.jpeg"}]}]