[{"e_id":"11389","title":"巴基斯坦立国运动领导人真纳逝世","content":"\n    在73年前的今天，1948年9月11日(农历1948年8月9日)，巴基斯坦立国运动领导人真纳逝世。全印穆斯林联盟主席M·A·真纳（右）与孟买省联盟主席昌德拉加真纳（1886～1948），穆罕默德·阿里·真纳。巴基斯坦立国运动领导人。生于卡拉奇。在英国伦敦林肯法学院学法律，在孟买高等法院当律师和临时推事。1906年参加国大党。1910年当选为印度中央立法议会议员。1913年参加印度穆斯林联盟，曾多次担任主席。早期主张印度建立统一的独立国家，协商订立印度大党和穆斯林联盟和解的协定；后因不满意国大党对待穆斯林的态度及甘地的非暴力和不合作抵抗运动，1920年与国大党决裂。1922年再次当选为印度中央立法议会议员，并作为印度穆斯林的唯一代表出席圆桌会议。1930年宣布穆斯林联盟是印度穆斯林的唯一代表性组织。1936年任穆斯林联盟中央选举委员会主席。后曾定居伦敦，在枢密院法庭重操律师业。1938年回到印度。1940年穆斯林联盟在拉哈尔举行代表大会，通过了真纳关于建立巴基斯坦的纲领，主张在穆斯林人口占多数地区摆脱英国的殖民统治，联合组成一个伊斯兰教的国家。1947年印巴分治后，出任巴基斯坦自治领第一任总督、制宪议会主席。翌年9月因心脏病突发而逝世。","picNo":"1","picUrl":[{"pic_title":"全印穆斯林联盟主席M·A·真纳（右）与孟买省联盟主席昌德拉加","suffix":"jpeg","id":1,"url":"https://aimgs.oss-cn-shenzhen.aliyuncs.com/history_2021/11389_1.jpeg"}]}]