[{"e_id":"12544","title":"2020年诺贝尔化学奖揭晓","content":"\n    2020年10月7日(农历2020年8月21日)，2020年诺贝尔化学奖揭晓。据诺贝尔奖官方网站消息，2020年诺贝尔化学奖于北京时间10月7日17时45分许正式揭晓，由法国科学家埃马纽埃尔·卡彭蒂耶（Emmanuelle Charpentier）与美国科学家詹妮弗·杜德纳（Jennifer A . Doudna）获得。以表彰她们“开发出一种基因组编辑方法”。两位获奖者将分享1000万瑞典克朗奖金（约合760万人民币）。&#13;\n&#13;\n埃马纽埃尔·卡彭蒂耶，就职于德国柏林马克斯·普朗克病原学研究室；詹妮弗·杜德纳，美国生物学家，加州大学伯克利分校的化学和分子生物学与细胞生物学教授。&#13;\n2020年诺贝尔奖六大奖项，包括诺贝尔生理学或医学奖、诺贝尔物理奖、诺贝尔化学奖、诺贝尔文学奖、诺贝尔和平奖、诺贝尔经济学奖，于10月5日至12日陆续揭晓。诺贝尔基金会首席执行官拉尔斯·海肯斯滕此前表示，受新冠疫情影响，今年12月将不再举行传统的诺贝尔奖颁奖典礼，颁奖仪式将改为线上举行。","picNo":"0","picUrl":[]}]