[{"e_id":"3432","title":"美国罗斯福总统签署《贷款和出租武器法案》","content":"\n    在80年前的今天，1941年3月11日(农历1941年2月14日)，美国罗斯福总统签署《贷款和出租武器法案》。\n\n\n罗斯福签署《租借法》\n《贷款和出租武器法案》又称《租借法》，是美国保证英国和所有被轴心势力侵略的国家予以战时援助的法案。1941年1月10日，美国政府将《租借法》草案提交国会审议，国会讨论并通过了此法。罗斯福总统于1941年3月11日签署了《租借法》。该法规定：任何国家只要总统认为其防务对美国国防至为重要”，就有资格通过美国的出售、转让、交换或租借方式取得任何防御物资。据此，美国向国外共提供了500亿美元的租借物资。其中60%提供给英国；32%提供给苏联。《租借法》对取得反法西斯战争的胜利起了重大作用。\n\n\n\n1776号“进一步增强美国防务及其他目标”法案\n\n\n点评：呵呵，不太了解美国历史，租借法对美国和全世界历史有啥意义?\n","picNo":"2","picUrl":[{"pic_title":"罗斯福签署《租借法》","suffix":"jpeg","id":1,"url":"https://aimgs.oss-cn-shenzhen.aliyuncs.com/history_2021/3432_1.jpeg"},{"pic_title":"1776号“进一步增强美国防务及其他目标”法案","suffix":"jpeg","id":2,"url":"https://aimgs.oss-cn-shenzhen.aliyuncs.com/history_2021/3432_2.jpeg"}]}]