[{"e_id":"2650","title":"多国部队向伊拉克军队发起地面进攻","content":"\n    在30年前的今天，1991年2月24日(农历1991年1月10日)，多国部队向伊拉克军队发起地面进攻。多国部队向伊拉克阵地发射多级火箭1991年2月24日凌晨4时（当地时间），以美国为首的多国部队兵分四路开始向科威特和伊拉克境内发起大规模地面进攻。26日中午，伊拉克总统萨达姆宣布从科威特撤军。 当晚6时，巴格达电台广播说，伊政府已同意无条件接受安理会12项决议。 27日晚9时，美国总统布什发表电视讲话， 宣布多国部队将于格林威治时间28日5时实行停火。持续了42天之久的海湾战争基本结束， 科威特在被占7个月之后，终于恢复了独立。美军飞机前往轰炸伊拉克科威特油井燃起冲天大火一名知道战友阵亡的美国伤兵失声痛哭","picNo":"4","picUrl":[{"pic_title":"多国部队向伊拉克阵地发射多级火箭","suffix":"jpeg","id":1,"url":"https://aimgs.oss-cn-shenzhen.aliyuncs.com/history_2021/2650_1.jpeg"},{"pic_title":"美军飞机前往轰炸伊拉克","suffix":"jpeg","id":2,"url":"https://aimgs.oss-cn-shenzhen.aliyuncs.com/history_2021/2650_2.jpeg"},{"pic_title":"科威特油井燃起冲天大火","suffix":"jpeg","id":3,"url":"https://aimgs.oss-cn-shenzhen.aliyuncs.com/history_2021/2650_3.jpeg"},{"pic_title":"一名知道战友阵亡的美国伤兵失声痛哭","suffix":"jpeg","id":4,"url":"https://aimgs.oss-cn-shenzhen.aliyuncs.com/history_2021/2650_4.jpeg"}]}]