[{"e_id":"19","title":"中国驻檀香山领事馆落成","content":"\n    在88年前的今天，1933年1月1日(农历1932年12月6日)，中国驻檀香山领事馆落成。\n\t1886年(清光绪十二年)肖政府委派程汝楫为驻檀香山首任领事。1898年檀香山归并美国，驻美大使伍廷芳奏请清政府正式设立领事，浙江同知杨蔚彬奉派抵行檀任职。中国驻檀领事馆，自清代至1931年均租赁为址，向无定所，迁徙频仍。后由当地侨界领袖杜惠生、陈巧等12人，组织筹捐购置领事馆费委员会，负责筹款修建，于1933年是日领事馆正式启用，由筹捐领馆费委员会名义赠送中国政府。1934年5月8日，驻檀香山领事馆升格为总领事馆。\n\n\n\t延伸阅读：老上海领事馆老照片\n\n\n\t \n\n\n\t延伸阅读：老上海领事馆老照片\n\n\n\t\n\n\t奥地利领事馆\n\n\t\n\n\t德国领事馆\n\n\t德国领事馆(GermanConsulate)。德国领事馆位于黄浦路9号，1852年正式设立，由外表十分相似的住宅楼和办公楼组成，并排座落在黄浦江边。1937年4月，德国领事馆迁到位于北京路和外滩交叉口的怡泰大楼办公，6月。旧楼被拆除，原计划在旧址上重建领事馆，随抗战告吹。\n\n\t\n\n\t俄国领事馆\n\n\t俄国领事馆建于1914年6月，1916年底竣工，位于与德国领事馆毗邻的礼查公园旧址上，紧邻黄浦江。大楼共有3层楼面，另有一个半地下室和一个楼顶层。立面用仿天然石料的混凝土饰板装饰，内部装修采用了柚木和大理石。\n\n\t\n\n\t法国领事馆\n\n\t1848年1月25日，法国第一任驻沪总领事敏体尼抵达上海，租法国天主教神甫赵主教住宅(今四川南路、金陵东路口)建立领事署。1864年在公馆马路(今金陵东路)外滩建造新馆，1867年建成，1894年又拆毁重建，为一幢法国文艺复兴风格的3层楼建筑。\n\n\t\n\n\t美国领事馆(1927年)\n\n\t\n\n\t日本领事馆\n\n\t日本领事馆，位于北扬子路1号(今扬子江路黄浦江边)，1872年正式设立。民国初年曾搬迁到西摩路15号(今陕西北路威海路转角)办公，并在武昌路另设一馆。20年代初搬回旧址，另建新馆。\n\n\t\n\n\t意大利领事馆\n\n\t意大利领事馆，位于静安寺路112号(今南京西路新昌路西)，1903年3月正式设立，是一幢2层楼建筑，中间部分3层，并带圆形顶部。第二次世界大战期间降格为驻沪代办处，1946年2月复为领事馆。\n\n\t\n\n\t英国领事馆\n\n\t1843年11月8日，英国驻沪第一领事巴富尔莅沪，以年租得城内姚家弄顾姓大宅一幢，作为领事署。1846年4月巴富尔聚资1万7千元购入李家庄一带(今北京东路、圆明园路近外滩处)百余土地建造领署，1849年7月建成，1870年12月毁于火灾。1872年又在原址重建新馆，主屋高2层，转木结构，面向草地的东面，中部有5孔券廊。建筑外貌具英国殖民地建筑风格。主屋北侧有一幢2层转木结构房屋，建于1882年，原为领事住宅，有廊与主屋相连。","picNo":"8","picUrl":[{"pic_title":"奥地利领事馆","suffix":"jpeg","id":1,"url":"https://aimgs.oss-cn-shenzhen.aliyuncs.com/history_2021/19_1.jpeg"},{"pic_title":"德国领事馆","suffix":"jpeg","id":2,"url":"https://aimgs.oss-cn-shenzhen.aliyuncs.com/history_2021/19_2.jpeg"},{"pic_title":"俄国领事馆","suffix":"jpeg","id":3,"url":"https://aimgs.oss-cn-shenzhen.aliyuncs.com/history_2021/19_3.jpeg"},{"pic_title":"法国领事馆","suffix":"jpeg","id":4,"url":"https://aimgs.oss-cn-shenzhen.aliyuncs.com/history_2021/19_4.jpeg"},{"pic_title":"美国领事馆(1927年)","suffix":"jpeg","id":5,"url":"https://aimgs.oss-cn-shenzhen.aliyuncs.com/history_2021/19_5.jpeg"},{"pic_title":"日本领事馆","suffix":"jpeg","id":6,"url":"https://aimgs.oss-cn-shenzhen.aliyuncs.com/history_2021/19_6.jpeg"},{"pic_title":"意大利领事馆","suffix":"jpeg","id":7,"url":"https://aimgs.oss-cn-shenzhen.aliyuncs.com/history_2021/19_7.jpeg"},{"pic_title":"英国领事馆","suffix":"jpeg","id":8,"url":"https://aimgs.oss-cn-shenzhen.aliyuncs.com/history_2021/19_8.jpeg"}]}]