[{"e_id":"3487","title":"中国“长寿之王”龚来发去世，终年147岁","content":"\n    在26年前的今天，1995年3月12日(农历1995年2月12日)，中国“长寿之王”龚来发去世，终年147岁。\n\t\n\n\t中国“长寿之王”龚来发\n\n\t1993年由全国老龄委领导承办的百岁老人调查，10月22日，中国百岁寿星座次排定。145岁的贵州仡佬族老寿星龚来发被授予“中国长寿之王(颐春茶杯)金座椅”的美称；122岁的广东老寿星孔英被授予“中国长寿王后(仁和杯)金手杖”的美称。\n\n\t被授予“中国长寿之王”的龚来发生于1848年3月，仡佬族，文盲，终生未婚，身高1.4米，体重30公斤。他半岁时丧父，因家庭贫穷，母亲把他抱给大包岭村的向家当儿子。现在赡养他的已是向家第七代人。据悉，龚来发一生务农，不喝酒，不抽烟，每天只吃两餐，每餐一小碗大米和玉米做的混合饭。老人住的地方，田少土多，风景秀丽，空气清新。周围几里无村庄，三面群山环抱，每座山都长满茂密的树林。这里的人大多能活到七八十岁。1995年3月12日，龚来发老人因患急性黄疸性肝炎，经多方抢救医治无效在贵州省务川仡佬族苗族自治县偏僻的茅天镇去世，终年147岁。","picNo":"1","picUrl":[{"pic_title":"中国“长寿之王”龚来发","suffix":"jpeg","id":1,"url":"https://aimgs.oss-cn-shenzhen.aliyuncs.com/history_2021/3487_1.jpeg"}]}]