[{"e_id":"223","title":"我国与吉尔吉斯斯坦建交","content":"\n    在29年前的今天，1992年1月5日(农历1991年12月1日)，我国与吉尔吉斯斯坦建立外交关系。\n\t\n\n\t楚河大街是吉尔吉斯斯坦首都比什凯克市最主要的街道。\n\n\t吉尔吉斯斯坦，位于中亚东北部。面积19.85万平方公里。人口454.68万人(1995)，共有80多个民族。其中吉尔吉斯族占52.4%，俄罗斯族占21.5%。国语为吉尔吉斯语，俄语为交际语言。\n\n\t首都比什凯克。吉尔吉斯斯坦经济以农牧业为主，是能源、原料型。吉尔吉斯斯坦在19世纪70年代并入俄罗斯。1917年11月建立苏维埃政权。1924年10月成立卡拉吉尔吉斯自治州，属俄联部。1926年2月成立吉尔吉斯苏维埃共和国。加入苏联。1990年12月发表主权宣言。1991年8月31日宣布独立。同年12月21日加入独联体。奉行永久中立和全面开放的政策，不参加任何军事集团。外交任务首在追求经济利益和人道利益。\n\n\t1992年1月5日与我国建交。\n\n\t\n\n\t皇家体育馆，比什凯克市内的皇家体育馆，是苏联解体前的建筑。\n\n\t\n\n\t奥什市场\n\n\t\n\n\t高原公路，雪山围绕下的公路绵延向远方。\n\n\t\n\n\t阿拉多广场，位于比什凯克市中心的阿拉多广场(Ala-Too Square)。\n\n\t\n\n\t晨光中的托木尔峰\n\n\t\n\n\t天高云低\n\n\t\n\n\t国旗，市区内随处可见吉尔吉斯斯坦的国旗。\n\n\t\n\n\t卡拉库里湖边的蒙古包\n\n\t\n\n\tYuzhnye Vorota公园纪念碑，比什凯克市区标志建筑之一。\n\n\t\n\n\t天山山脉，天山古名白山，又名雪山，因冬夏有雪，才有此名。\n\n\t\n\n\t冰川与雪山\n\n\t\n\n\t远山，近城，近处市区高楼林立，远方，天山山脉巍峨耸立，直冲云端。\n\n\t\n\n\t婚车，比什凯克市，一场婚礼正要举行。\n\n\t\n\n\t换岗，阿拉多广场，警卫正在换岗。\n\n\t\n\n\t小男孩，年纪尚小，却已有了与年龄不符的高原红。\n\n\t\n\n\t逐，年轻的牧人策马奔腾，群马在其带领下肆意驰骋。\n\n\t\n\n\t牧民生活，蒙古包内，一壶奶茶，一盘馕饼。\n\n\t\n\n\t红白，雪山下，两名身着艳红色传统服饰的美女分外惹眼。\n\n\t\n\n\t传统帽子，吉尔吉斯斯坦牧民传统帽饰。\n\n\t\n\n\t比什凯克市集，吉尔吉斯斯坦的服装市场里售卖各式服装，深受西方游客喜爱。\n\n\t\n\n\t地毯，吉尔吉斯斯坦手工制地毯，色泽鲜艳，工艺精湛。\n\n\t\n\n\t国产红酒，印有好莱坞女星照片的吉国国产红酒。\n\n\t\n\n\t羊毛制手工艺品\n\n\t\n\n\t农产品，农产品是吉尔吉斯斯坦的主要出口商品之一。\n\n\t\n\n\t到达大厅，比什凯克玛纳斯机场的到达大厅。\n\n\t\n\n\t比什凯克火车站\n\n\t\n\n\t训练，吉尔吉斯斯坦年轻男子入伍接受军事训练。\n\n\t\n\n\t军校，位于比什凯克市区的航空军事学校。\n\n\t\n\n\t女兵，吉尔吉斯斯坦女兵在冰天雪地中进行火箭炮发射训练\n\n\t\n\n\t边防战士，吉尔吉斯斯坦南部边防战士列队行进。","picNo":"31","picUrl":[{"pic_title":"楚河大街是吉尔吉斯斯坦首都比什凯克市最主要的街道。","suffix":"jpeg","id":1,"url":"https://aimgs.oss-cn-shenzhen.aliyuncs.com/history_2021/223_1.jpeg"},{"pic_title":"皇家体育馆，比什凯克市内的皇家体育馆，是苏联解体前的建筑。","suffix":"jpeg","id":2,"url":"https://aimgs.oss-cn-shenzhen.aliyuncs.com/history_2021/223_2.jpeg"},{"pic_title":"奥什市场","suffix":"jpeg","id":3,"url":"https://aimgs.oss-cn-shenzhen.aliyuncs.com/history_2021/223_3.jpeg"},{"pic_title":"高原公路，雪山围绕下的公路绵延向远方。","suffix":"jpeg","id":4,"url":"https://aimgs.oss-cn-shenzhen.aliyuncs.com/history_2021/223_4.jpeg"},{"pic_title":"阿拉多广场，位于比什凯克市中心的阿拉多广场(Ala-Too Square)。","suffix":"jpeg","id":5,"url":"https://aimgs.oss-cn-shenzhen.aliyuncs.com/history_2021/223_5.jpeg"},{"pic_title":"晨光中的托木尔峰","suffix":"jpeg","id":6,"url":"https://aimgs.oss-cn-shenzhen.aliyuncs.com/history_2021/223_6.jpeg"},{"pic_title":"天高云低","suffix":"jpeg","id":7,"url":"https://aimgs.oss-cn-shenzhen.aliyuncs.com/history_2021/223_7.jpeg"},{"pic_title":"国旗，市区内随处可见吉尔吉斯斯坦的国旗。","suffix":"jpeg","id":8,"url":"https://aimgs.oss-cn-shenzhen.aliyuncs.com/history_2021/223_8.jpeg"},{"pic_title":"卡拉库里湖边的蒙古包","suffix":"jpeg","id":9,"url":"https://aimgs.oss-cn-shenzhen.aliyuncs.com/history_2021/223_9.jpeg"},{"pic_title":"Yuzhnye Vorota公园纪念碑，比什凯克市区标志建筑之一。","suffix":"jpeg","id":10,"url":"https://aimgs.oss-cn-shenzhen.aliyuncs.com/history_2021/223_10.jpeg"},{"pic_title":"天山山脉，天山古名白山，又名雪山，因冬夏有雪，才有此名。","suffix":"jpeg","id":11,"url":"https://aimgs.oss-cn-shenzhen.aliyuncs.com/history_2021/223_11.jpeg"},{"pic_title":"冰川与雪山","suffix":"jpeg","id":12,"url":"https://aimgs.oss-cn-shenzhen.aliyuncs.com/history_2021/223_12.jpeg"},{"pic_title":"远山，近城，近处市区高楼林立，远方，天山山脉巍峨耸立，直冲云端。","suffix":"jpeg","id":13,"url":"https://aimgs.oss-cn-shenzhen.aliyuncs.com/history_2021/223_13.jpeg"},{"pic_title":"婚车，比什凯克市，一场婚礼正要举行。","suffix":"jpeg","id":14,"url":"https://aimgs.oss-cn-shenzhen.aliyuncs.com/history_2021/223_14.jpeg"},{"pic_title":"换岗，阿拉多广场，警卫正在换岗。","suffix":"jpeg","id":15,"url":"https://aimgs.oss-cn-shenzhen.aliyuncs.com/history_2021/223_15.jpeg"},{"pic_title":"小男孩，年纪尚小，却已有了与年龄不符的高原红。","suffix":"jpeg","id":16,"url":"https://aimgs.oss-cn-shenzhen.aliyuncs.com/history_2021/223_16.jpeg"},{"pic_title":"逐，年轻的牧人策马奔腾，群马在其带领下肆意驰骋。","suffix":"jpeg","id":17,"url":"https://aimgs.oss-cn-shenzhen.aliyuncs.com/history_2021/223_17.jpeg"},{"pic_title":"牧民生活，蒙古包内，一壶奶茶，一盘馕饼。","suffix":"jpeg","id":18,"url":"https://aimgs.oss-cn-shenzhen.aliyuncs.com/history_2021/223_18.jpeg"},{"pic_title":"红白，雪山下，两名身着艳红色传统服饰的美女分外惹眼。","suffix":"jpeg","id":19,"url":"https://aimgs.oss-cn-shenzhen.aliyuncs.com/history_2021/223_19.jpeg"},{"pic_title":"传统帽子，吉尔吉斯斯坦牧民传统帽饰。","suffix":"jpeg","id":20,"url":"https://aimgs.oss-cn-shenzhen.aliyuncs.com/history_2021/223_20.jpeg"},{"pic_title":"比什凯克市集，吉尔吉斯斯坦的服装市场里售卖各式服装，深受西方游客喜爱。","suffix":"jpeg","id":21,"url":"https://aimgs.oss-cn-shenzhen.aliyuncs.com/history_2021/223_21.jpeg"},{"pic_title":"地毯，吉尔吉斯斯坦手工制地毯，色泽鲜艳，工艺精湛。","suffix":"jpeg","id":22,"url":"https://aimgs.oss-cn-shenzhen.aliyuncs.com/history_2021/223_22.jpeg"},{"pic_title":"国产红酒，印有好莱坞女星照片的吉国国产红酒。","suffix":"jpeg","id":23,"url":"https://aimgs.oss-cn-shenzhen.aliyuncs.com/history_2021/223_23.jpeg"},{"pic_title":"羊毛制手工艺品","suffix":"jpeg","id":24,"url":"https://aimgs.oss-cn-shenzhen.aliyuncs.com/history_2021/223_24.jpeg"},{"pic_title":"农产品，农产品是吉尔吉斯斯坦的主要出口商品之一。","suffix":"jpeg","id":25,"url":"https://aimgs.oss-cn-shenzhen.aliyuncs.com/history_2021/223_25.jpeg"},{"pic_title":"到达大厅，比什凯克玛纳斯机场的到达大厅。","suffix":"jpeg","id":26,"url":"https://aimgs.oss-cn-shenzhen.aliyuncs.com/history_2021/223_26.jpeg"},{"pic_title":"比什凯克火车站","suffix":"jpeg","id":27,"url":"https://aimgs.oss-cn-shenzhen.aliyuncs.com/history_2021/223_27.jpeg"},{"pic_title":"训练，吉尔吉斯斯坦年轻男子入伍接受军事训练。","suffix":"jpeg","id":28,"url":"https://aimgs.oss-cn-shenzhen.aliyuncs.com/history_2021/223_28.jpeg"},{"pic_title":"军校，位于比什凯克市区的航空军事学校。","suffix":"jpeg","id":29,"url":"https://aimgs.oss-cn-shenzhen.aliyuncs.com/history_2021/223_29.jpeg"},{"pic_title":"女兵，吉尔吉斯斯坦女兵在冰天雪地中进行火箭炮发射训练","suffix":"jpeg","id":30,"url":"https://aimgs.oss-cn-shenzhen.aliyuncs.com/history_2021/223_30.jpeg"},{"pic_title":"边防战士，吉尔吉斯斯坦南部边防战士列队行进。","suffix":"jpeg","id":31,"url":"https://aimgs.oss-cn-shenzhen.aliyuncs.com/history_2021/223_31.jpeg"}]}]