[{"e_id":"877","title":"知名的法国设计师菲力浦·史塔克出生","content":"\n    在72年前的今天，1949年1月18日(农历1948年12月20日)，知名的法国设计师菲力浦·史塔克出生。菲力浦·史塔克，1948年1月18日在巴黎出生，父亲是 一名飞行员及飞机工程师，考进巴黎的Ecole Nissim de Camondo学院，主修建筑。毕业后在皮尔.卡丹担任艺术指导一职，不久他便成立自己的公司，这时他设计的三脚椅子 和Cafe Costes内的布置，使他逐渐受到人们的注意。 1982年负责法国总统密特朗新居的设计工作，1984年他接受了爱丽舍宫的任命，由于这些项目的宣传和支持，斯达克跻身于设计大师的行列。最新动作是与法国著名邮购集团La Redoute合作，推出\"Good Good\"系列，包括家具、时装、灯饰、儿童玩具和食品，换言之是出售一整套史塔克的生活方式。","picNo":"1","picUrl":[{"pic_title":"","suffix":"jpeg","id":1,"url":"https://aimgs.oss-cn-shenzhen.aliyuncs.com/history_2021/877_1.jpeg"}]}]