[{"e_id":"881","title":"一江山岛登陆战","content":"\n    在66年前的今天，1955年1月18日(农历1954年12月25日)，一江山岛登陆战。中国人民解放军空军部队首次投入机群掩护登陆部队1955年1月18日，为了打击国民党军的嚣张气焰，实现中央军委解放浙江东南沿海岛屿的决心，人民解放军华东军区以步兵1个师、各种类型舰艇137艘、航空兵22个大队，于1月18日发起了一江山岛登陆作战。整个一江山岛渡登陆作战历时10个小时，共打死国民党军519人，俘虏567人，击沉军舰3艘，击伤4艘。一江山岛被攻克后，盘踞在大陈各岛屿的国民党军失去了外围屏障，被迫在美国武装力量掩护下裹胁岛上居民近二万人逃往台湾。一江山岛渡海登陆作战，虽然规模不大，但影响深远。这是我陆、海、空三军首次对近海岛屿之敌的联合作战，取得了非常宝贵的协同登陆作战经验，为全部解放浙江沿海岛屿打响了胜利的第一炮。","picNo":"1","picUrl":[{"pic_title":"中国人民解放军空军部队首次投入机群掩护登陆部队","suffix":"jpeg","id":1,"url":"https://aimgs.oss-cn-shenzhen.aliyuncs.com/history_2021/881_1.jpeg"}]}]