[{"day":"4/23","date":"699年4月23日","title":"唐代嫁吐谷浑王诺曷钵的弘化公主去世","e_id":"5189"},{"day":"4/23","date":"1200年4月23日","title":"中国思想家、文学家朱熹逝世","e_id":"5190"},{"day":"4/23","date":"1564年4月23日","title":"莎士比亚诞辰","e_id":"5191"},{"day":"4/23","date":"1616年4月23日","title":"塞万提斯逝世","e_id":"5192"},{"day":"4/23","date":"1616年4月23日","title":"中国文学家汤显祖逝世","e_id":"5193"},{"day":"4/23","date":"1794年4月23日","title":"中国思想家、文学家魏源诞生","e_id":"5194"},{"day":"4/23","date":"1847年4月23日","title":"一代京师“伶王”谭鑫培诞生","e_id":"5195"},{"day":"4/23","date":"1858年4月23日","title":"德国物理学家普朗克诞生","e_id":"5196"},{"day":"4/23","date":"1877年4月23日","title":"中国政治家廖仲恺诞辰","e_id":"5197"},{"day":"4/23","date":"1891年4月23日","title":"苏联作曲家普罗科菲耶夫诞辰","e_id":"5198"},{"day":"4/23","date":"1902年4月23日","title":"冰岛小说家拉克斯内斯诞辰","e_id":"5199"},{"day":"4/23","date":"1910年4月23日","title":"汪精卫等谋刺载沣未遂被捕","e_id":"5200"},{"day":"4/23","date":"1928年4月23日","title":"超级童星秀兰·邓波儿出生","e_id":"5201"},{"day":"4/23","date":"1945年4月23日","title":"中共第七次全国代表大会开幕","e_id":"5202"},{"day":"4/23","date":"1946年4月23日","title":"作家教育家夏眄尊逝世","e_id":"5203"},{"day":"4/23","date":"1949年4月23日","title":"人民解放军突破千里江防 毛泽东赋诗追穷寇","e_id":"5204"},{"day":"4/23","date":"1949年4月23日","title":"中国人民解放军海军诞生","e_id":"5205"},{"day":"4/23","date":"1951年4月23日","title":"相声演员常宝堃在朝鲜牺牲","e_id":"5206"},{"day":"4/23","date":"1956年4月23日","title":"第一种国产喷气式歼击机试制成功","e_id":"5207"},{"day":"4/23","date":"1960年4月23日","title":"我国第一艘万吨轮下水","e_id":"5208"},{"day":"4/23","date":"1969年4月23日","title":"电影艺术家郑君里受迫致死","e_id":"5209"},{"day":"4/23","date":"1970年4月23日","title":"我国著名女新闻工作者浦熙修逝世","e_id":"5210"},{"day":"4/23","date":"1974年4月23日","title":"葡萄牙“尉官运动”发动“红色革命”","e_id":"5211"},{"day":"4/23","date":"1975年4月23日","title":"锡金被并入印度","e_id":"5212"},{"day":"4/23","date":"1975年4月23日","title":"南越内阁辞职，美国总统宣布越南战争结束","e_id":"5213"},{"day":"4/23","date":"1977年4月23日","title":"北海油井爆炸 海洋遭受污染","e_id":"5214"},{"day":"4/23","date":"1979年4月23日","title":"王守信贪污巨款案被破获","e_id":"5215"},{"day":"4/23","date":"1980年4月23日","title":"中共中央废除干部终身制","e_id":"5216"},{"day":"4/23","date":"1984年4月23日","title":"美法两国发现同一种爱滋病毒","e_id":"5217"},{"day":"4/23","date":"1985年4月23日","title":"可口可乐宣布将上市新可乐","e_id":"5218"},{"day":"4/23","date":"1987年4月23日","title":"天津大邱庄成为中国最早的亿元村","e_id":"5219"},{"day":"4/23","date":"1989年4月23日","title":"中国早期电影明星胡蝶在加拿大逝世","e_id":"5220"},{"day":"4/23","date":"1992年4月23日","title":"联合国年度报告指出世界贫富差距加剧","e_id":"5221"},{"day":"4/23","date":"1995年4月23日","title":"世界读书日","e_id":"5222"},{"day":"4/23","date":"1996年4月23日","title":"徐虎事迹在全国引起巨大反响","e_id":"5223"},{"day":"4/23","date":"1999年4月23日","title":"北约纪念成立50周年 确立联盟新战略","e_id":"5224"},{"day":"4/23","date":"2007年4月23日","title":"俄罗斯前总统叶利钦去世","e_id":"5225"},{"day":"4/23","date":"2013年4月23日","title":"新疆巴楚县发生暴力恐怖案","e_id":"5226"},{"day":"4/23","date":"2019年4月23日","title":"哈勃发现神秘星系水母","e_id":"5227"},{"day":"4/23","date":"2019年4月23日","title":"中国首例核辐射案受害者离世","e_id":"5228"}]