[{"e_id":"5390","title":"《绿野仙踪》上映","content":"\n    在82年前的今天，1939年4月27日(农历1939年3月8日)，《绿野仙踪》上映。《绿野仙踪》剧照1939年，美国有两部经典影片问世。一部是风靡全球的《乱世佳人》，另一部就是老少咸宜的童话故事片《绿野仙踪》。这两部影片都出自同一位导演维克多-弗莱明之后。《绿野仙踪》于1939年由美国米高梅公司首次推出，它改编自弗兰克-鲍姆的儿童经典读物《奇妙的奥兹男巫》。16岁的裘迪-嘉伦担任女主演，其他主要演员还有弗兰克-摩根、雷-博尔格、伯特-拉尔、杰克-哈利、比莉-伯克和玛格丽特-汉密尔顿。《绿野仙踪》讲述的是多萝西-盖尔对她在埃姆姨妈和亨利叔叔的堪萨斯农场的生活感到不满，打算出走。这时，她被一股龙卷风吹倒在地，昏迷不醒。更令人惊奇的是，多萝西的整座房屋都被卷入烟囱散发的烟雾中，并恰好落在奥兹仙境芒奇金城邪恶的已故东方女巫的头上。当多萝西从她的房子里走出来时，她遇到这块陌生土地上令人惊奇的居民--包括芒奇金城的市民们和善良的北方女巫格林达。多萝西在和邪恶的西方女巫发生口角后，便什么也不想做了，只想回家。但格林劝她还是先去拜访神秘的奥兹男巫--他就住在黄砖路的尽头，而且有魔力实现一切愿望。多萝西在踏上她的旅途之前和几个伙伴聚集在一起，他们也是想寻求男巫帮助的。这几个伙伴是稻草人（想要一个头脑）、伐木洋铁人（想要一个心脏）和怯懦的狮子（想要勇气）。多萝西和伙伴们避开了邪恶的女巫，终于来到美丽的绿宝石城中男巫的院子。然而，强有力的奥兹告诉他们：在实现他们的愿望之前，他们首先必须证明他们想要的东西是应该得到的--这就需要将邪恶的女巫的扫帚把带到他面前。虽然多萝西被飞猴俘虏，但她还是勇气十足地战胜了女巫。当他们胜利地返回男巫处时，却惊奇地发现他不过是个江湖郎中。但是男巫向他们证明：他们都得到了自己所追求的东西。至于多萝西的请求--他能用他的气球送她回堪萨斯州。然而气球未能带多萝西起飞，她在格林达的指导下使用有魔力的红拖鞋返回家乡。现在，多萝西终于心满意足地向她的家人和朋友宣布：”世界上再也没有别的地方比得上自己的家。”1998年11月，为纪念《绿野仙踪》问世60周年，经过数字化技术处理的《绿野仙踪》再度上映。华纳兄弟影片公司在《绿野仙踪》问世60周年前夕，十分自豪地重新发行了这部受到人们广泛喜爱的经典片的特别版，而电影仍幸看到这部影片在大银幕上再次公映。这个特别版经过技术处理增加了艺术魅力。影片使用数字技术修复拷贝，并使音响具有立体声效果。《绿野仙踪》剧照《绿野仙踪》剧照《绿野仙踪》剧照《绿野仙踪》剧照因在《绿野仙踪》中饰多萝西闻名天下裘娣·嘉伦","picNo":"6","picUrl":[{"pic_title":"《绿野仙踪》剧照","suffix":"jpeg","id":1,"url":"https://aimgs.oss-cn-shenzhen.aliyuncs.com/history_2021/5390_1.jpeg"},{"pic_title":"《绿野仙踪》剧照","suffix":"jpeg","id":2,"url":"https://aimgs.oss-cn-shenzhen.aliyuncs.com/history_2021/5390_2.jpeg"},{"pic_title":"《绿野仙踪》剧照","suffix":"jpeg","id":3,"url":"https://aimgs.oss-cn-shenzhen.aliyuncs.com/history_2021/5390_3.jpeg"},{"pic_title":"《绿野仙踪》剧照","suffix":"jpeg","id":4,"url":"https://aimgs.oss-cn-shenzhen.aliyuncs.com/history_2021/5390_4.jpeg"},{"pic_title":"《绿野仙踪》剧照","suffix":"jpeg","id":5,"url":"https://aimgs.oss-cn-shenzhen.aliyuncs.com/history_2021/5390_5.jpeg"},{"pic_title":"因在《绿野仙踪》中饰多萝西闻名天下裘娣·嘉伦","suffix":"jpeg","id":6,"url":"https://aimgs.oss-cn-shenzhen.aliyuncs.com/history_2021/5390_6.jpeg"}]}]